{"left":{"minX":{"x":162.0,"y":-299.0},"maxX":{"x":186.0,"y":-263.0},"minY":{"x":168.0,"y":-303.0},"maxY":{"x":176.0,"y":-255.0},"side":"LEFT","isCameraInverted":false},"right":{"minX":{"x":255.0,"y":-261.0},"maxX":{"x":284.0,"y":-297.0},"minY":{"x":271.0,"y":-301.0},"maxY":{"x":265.0,"y":-250.0},"side":"RIGHT","isCameraInverted":false}}
{"left":{"minX":{"x":348.0,"y":-283.0},"maxX":{"x":369.0,"y":-254.0},"minY":{"x":359.0,"y":-295.0},"maxY":{"x":356.0,"y":-245.0},"side":"LEFT","isCameraInverted":false},"right":{"minX":{"x":444.0,"y":-248.0},"maxX":{"x":476.0,"y":-288.0},"minY":{"x":462.0,"y":-293.0},"maxY":{"x":450.0,"y":-244.0},"side":"RIGHT","isCameraInverted":false}}
